contrib/README.rst
contrib/export_subscribers.sql
django_newsletter-1.2.1.dist-info/licenses/COPYRIGHT
django_newsletter-1.2.1.dist-info/licenses/LICENSE
docs/Makefile
docs/conf.py
docs/graph_models.dot
docs/graph_models.pdf
docs/graph_models.png
docs/index.rst
docs/installation.rst
docs/make.bat
docs/reference.rst
docs/requirements.txt
docs/settings.rst
docs/templates.rst
docs/upgrading.rst
docs/usage.rst
newsletter/__init__.py
newsletter/admin.py
newsletter/admin_forms.py
newsletter/admin_utils.py
newsletter/apps.py
newsletter/converters.py
newsletter/fields.py
newsletter/forms.py
newsletter/models.py
newsletter/settings.py
newsletter/urls.py
newsletter/utils.py
newsletter/validators.py
newsletter/views.py
newsletter/addressimport/__init__.py
newsletter/addressimport/parsers.py
newsletter/jobs/__init__.py
newsletter/jobs/daily/__init__.py
newsletter/jobs/hourly/__init__.py
newsletter/jobs/hourly/submit.py
newsletter/jobs/monthly/__init__.py
newsletter/jobs/weekly/__init__.py
newsletter/locale/ar/LC_MESSAGES/django.mo
newsletter/locale/ar/LC_MESSAGES/django.po
newsletter/locale/ar/LC_MESSAGES/djangojs.mo
newsletter/locale/ar/LC_MESSAGES/djangojs.po
newsletter/locale/cs_CZ/LC_MESSAGES/django.mo
newsletter/locale/cs_CZ/LC_MESSAGES/django.po
newsletter/locale/cs_CZ/LC_MESSAGES/djangojs.mo
newsletter/locale/cs_CZ/LC_MESSAGES/djangojs.po
newsletter/locale/de/LC_MESSAGES/django.mo
newsletter/locale/de/LC_MESSAGES/django.po
newsletter/locale/de/LC_MESSAGES/djangojs.mo
newsletter/locale/de/LC_MESSAGES/djangojs.po
newsletter/locale/el_GR/LC_MESSAGES/django.mo
newsletter/locale/el_GR/LC_MESSAGES/django.po
newsletter/locale/el_GR/LC_MESSAGES/djangojs.mo
newsletter/locale/el_GR/LC_MESSAGES/djangojs.po
newsletter/locale/en/LC_MESSAGES/django.mo
newsletter/locale/en/LC_MESSAGES/django.po
newsletter/locale/en/LC_MESSAGES/djangojs.mo
newsletter/locale/en/LC_MESSAGES/djangojs.po
newsletter/locale/es/LC_MESSAGES/django.mo
newsletter/locale/es/LC_MESSAGES/django.po
newsletter/locale/es/LC_MESSAGES/djangojs.mo
newsletter/locale/es/LC_MESSAGES/djangojs.po
django_newsletter-1.2.1.dist-info/METADATA
django_newsletter-1.2.1.dist-info/WHEEL
django_newsletter-1.2.1.dist-info/top_level.txt
django_newsletter-1.2.1.dist-info/RECORD
