Metadata-Version: 2.4
Name: django-newsletter
Version: 1.2.1
Summary: Django app for managing multiple mass-mailing lists with both plaintext as well as HTML templates (and pluggable WYSIWYG editors for messages), images and a smart queueing system all right from the admin interface.
Author-email: Mathijs de Bruin <mathijs@mathijsfietst.nl>
License-Expression: AGPL-3.0-or-later
Project-URL: Homepage, https://github.com/jazzband/django-newsletter/
Classifier: Development Status :: 6 - Mature
Classifier: Environment :: Web Environment
Classifier: Framework :: Django
Classifier: Framework :: Django :: 4.2
Classifier: Framework :: Django :: 5.2
Classifier: Intended Audience :: Developers
Classifier: Operating System :: OS Independent
Classifier: Programming Language :: Python
Classifier: Programming Language :: Python :: 3
Classifier: Programming Language :: Python :: 3.9
Classifier: Programming Language :: Python :: 3.10
Classifier: Programming Language :: Python :: 3.11
Classifier: Programming Language :: Python :: 3.12
Classifier: Programming Language :: Python :: 3.13
Classifier: Programming Language :: Python :: 3 :: Only
Classifier: Topic :: Utilities
Requires-Python: >=3.9
License-File: LICENSE
License-File: COPYRIGHT
Requires-Dist: Django>=4.2
Requires-Dist: chardet
Requires-Dist: Pillow
Provides-Extra: test
Requires-Dist: python-ldap; extra == "test"
Requires-Dist: unicodecsv; extra == "test"
Requires-Dist: python-card-me; extra == "test"
Requires-Dist: django-tinymce; extra == "test"
Requires-Dist: django-imperavi; extra == "test"
Dynamic: license-file
